__init__.py
example/mpl_secondary_y_axis.py
example/svg_report.py
example/test_time.py
example/tui.py
example/webapi_rest_get_tabular_trend_custom_config.py
pipeline/__init__.py
pipeline/__main__.py
pipeline/_version.py
pipeline/appdata_setup.py
pipeline/calls.py
pipeline/cli.py
pipeline/config_via_web.py
pipeline/configrationmanager.py
pipeline/create_sensors_db.py
pipeline/decorators.py
pipeline/env.py
pipeline/gui_litestar_msgspec_plotly.py
pipeline/gui_mpl_live.py
pipeline/gui_plotly_static.py
pipeline/gui_starlette_msgspec_plotly.py
pipeline/guiconfig.py
pipeline/helpers.py
pipeline/logging_setup.py
pipeline/pastehelpers.py
pipeline/pex-resource-loader-entry-point.py
pipeline/philosophy.py
pipeline/pipeline-winreg-filler-based-on-filetype.py
pipeline/plotbuffer.py
pipeline/plottools.py
pipeline/points_loader.py
pipeline/pyz-builder.py
pipeline/queriesmanager.py
pipeline/security_and_config.py
pipeline/state_manager.py
pipeline/system_info.py
pipeline/termux_setup.py
pipeline/time_manager.py
pipeline/variable_clarity.py
pipeline/version_info.py
pipeline/windows_setup.py
pipeline/workspace_manager.py
pipeline/api/__init__.py
pipeline/api/mission.py
pipeline/api/mission_opcua.py
pipeline/api/rjn.py
pipeline/api/status_api.py
pipeline/api/eds/__init__.py
pipeline/api/eds/config.py
pipeline/api/eds/core.py
pipeline/api/eds/database.py
pipeline/api/eds/exceptions.py
pipeline/api/eds/imports_historic.py
pipeline/api/eds/security.py
pipeline/api/eds/mock/client.py
pipeline/api/eds/mock/hold__init__.py
pipeline/api/eds/mock/points.py
pipeline/api/eds/mock/session.py
pipeline/api/eds/mock/trend.py
pipeline/api/eds/rest/__init__.py
pipeline/api/eds/rest/alarm.py
pipeline/api/eds/rest/client.py
pipeline/api/eds/rest/config.py
pipeline/api/eds/rest/demo.py
pipeline/api/eds/rest/graphics.py
pipeline/api/eds/rest/demo_/__init__.py
pipeline/api/eds/soap/__init__.py
pipeline/api/eds/soap/client.py
pipeline/api/eds/soap/config.py
pipeline/api/eds/soap/demo.py
pipeline_eds-0.4.4.dist-info/licenses/LICENSE
pipeline_eds-0.4.4.dist-info/METADATA
pipeline_eds-0.4.4.dist-info/WHEEL
pipeline_eds-0.4.4.dist-info/entry_points.txt
pipeline_eds-0.4.4.dist-info/top_level.txt
pipeline_eds-0.4.4.dist-info/RECORD
