Metadata-Version: 2.4
Name: pipeline-eds
Version: 0.4.4
Summary: A Python API pipeline library and CLI toolkit for Emerson Ovation EDS systems — built for engineers, control technicians, and wastewater SCADA teams.
Author-email: George Clayton Bennett <george.bennett@memphistn.gov>
License: MIT
Requires-Python: <3.15,>=3.9
License-File: LICENSE
Requires-Dist: backports.tarfile>=1.2
Requires-Dist: colorama>=0.4.6
Requires-Dist: distro>=1.9.0
Requires-Dist: keyring>=25.6.0; python_version >= "3.9" and platform_machine != "aarch64"
Requires-Dist: keyrings-alt>=5.0.2; platform_machine != "aarch64"
Requires-Dist: pendulum>=3.1.0; python_version >= "3.9"
Requires-Dist: plotly>=6.2.0
Requires-Dist: pyhabitat>=1.0.40
Requires-Dist: pyyaml<7.0.0,>=6.0.2
Requires-Dist: requests<3.0.0,>=2.32.3
Requires-Dist: rich>=14.1.0; python_version >= "3.10"
Requires-Dist: rich>=10.14.0; python_version < "3.10"
Requires-Dist: suds-py3>=1.4.5.0
Requires-Dist: msgspec>=0.19.0; python_version >= "3.9"
Requires-Dist: starlette>=0.50.0; python_version >= "3.10"
Requires-Dist: starlette>=0.47.3; python_version == "3.9.*"
Requires-Dist: typer>=0.17.4
Requires-Dist: tzdata>=2025.2
Requires-Dist: urllib3>=2.4.0; python_version >= "3.9"
Requires-Dist: uvicorn>=0.34.3; python_version >= "3.9"
Requires-Dist: python-multipart>=0.0.20
Requires-Dist: toml>=0.10.2
Provides-Extra: localdb-fallback-windows
Requires-Dist: pyodbc>=5.1.0; extra == "localdb-fallback-windows"
Requires-Dist: mysql-connector-python>=9.3.0; python_version >= "3.9" and extra == "localdb-fallback-windows"
Dynamic: license-file
